ulid/__init__.py
ulid/ulid.py
py_ulid-1.0.0.dist-info/LICENSE
py_ulid-1.0.0.dist-info/METADATA
py_ulid-1.0.0.dist-info/WHEEL
py_ulid-1.0.0.dist-info/top_level.txt
py_ulid-1.0.0.dist-info/RECORD
