Metadata-Version: 2.1
Name: py-ulid
Version: 1.0.0
Summary: Python library that provides an implementation of ULID Specification
Home-page: https://github.com/tsmanikandan/py-ulid
Author: Manikandan Sundararajan
Author-email: me@tsmanikandan.com
License: MIT
Platform: UNKNOWN
Classifier: License :: OSI Approved :: MIT License
Classifier: Programming Language :: Python :: 3
Classifier: Programming Language :: Python :: 3.6
Classifier: Operating System :: OS Independent
